shahienetal/BeegsAndBrell.py
shahienetal/DepthSurvey.py
shahienetal/FluidProperties.py
shahienetal/Solving_Intersections.py
shahienetal/TraverseCurve.py
shahienetal/Vogel.py
shahienetal/WaterProps.py
shahienetal/__init__.py
shahienetal-2.dist-info/LICENSE.txt
shahienetal-2.dist-info/METADATA
shahienetal-2.dist-info/WHEEL
shahienetal-2.dist-info/top_level.txt
shahienetal-2.dist-info/RECORD
